karp/__init__.py
karp/client.py
karp/request.py
karp/response.py
karp/server.py
karp/utils.py
karp-0.0.14.dist-info/METADATA
karp-0.0.14.dist-info/WHEEL
karp-0.0.14.dist-info/top_level.txt
karp-0.0.14.dist-info/RECORD
