Metadata-Version: 2.1
Name: karp
Version: 0.0.14
Summary: KARP Communication Protocol
Home-page: https://github.com/tooxo/karp
Author: tooxo
Author-email: till@s.chulte.de
License: None
Platform: UNKNOWN
